_cffi_backend-stubs/METADATA.toml
_cffi_backend-stubs/__init__.pyi
_cffi_backend-stubs/py.typed
cffi-stubs/METADATA.toml
cffi-stubs/__init__.pyi
cffi-stubs/api.pyi
cffi-stubs/backend_ctypes.pyi
cffi-stubs/cffi_opcode.pyi
cffi-stubs/commontypes.pyi
cffi-stubs/cparser.pyi
cffi-stubs/error.pyi
cffi-stubs/ffiplatform.pyi
cffi-stubs/lock.pyi
cffi-stubs/model.pyi
cffi-stubs/pkgconfig.pyi
cffi-stubs/py.typed
cffi-stubs/recompiler.pyi
cffi-stubs/setuptools_ext.pyi
cffi-stubs/vengine_cpy.pyi
cffi-stubs/vengine_gen.pyi
cffi-stubs/verifier.pyi
types_cffi-1.17.0.20250914.dist-info/licenses/LICENSE
types_cffi-1.17.0.20250914.dist-info/METADATA
types_cffi-1.17.0.20250914.dist-info/WHEEL
types_cffi-1.17.0.20250914.dist-info/top_level.txt
types_cffi-1.17.0.20250914.dist-info/RECORD
